kmex/__init__.py
kmex-1.0.dist-info/METADATA
kmex-1.0.dist-info/WHEEL
kmex-1.0.dist-info/top_level.txt
kmex-1.0.dist-info/RECORD
