Metadata-Version: 2.1
Name: kmex
Version: 1.0
Summary: model explainability
Home-page: UNKNOWN
Author: subhrajit mohanty
Author-email: subhrajit.mohanty@katonic.ai
License: MIT
Platform: UNKNOWN
Requires-Python: >=3.7, <4
Requires-Dist: alibi-detect (==0.7.1)
